<mindmap outcome='bad outcome'>
  <title>Outcome Prediction</title>
  <date>Mon May 15 09:48:51 AM CDT 2023
</date>
  <time>09:48
</time>
  <neuromap>
    <row>+--------------------------------------------------+</row>
    <row>|.....................................Bad.Outcome..|</row>
    <row>|.Other.Outcome....................../.............|</row>
    <row>|.+......................Software.Bug..............|</row>
    <row>|..\..................../..........................|</row>
    <row>|...\................../...........................|</row>
    <row>|....\................/............................|</row>
    <row>|.....\............../.............................|</row>
    <row>|......+------------+..............................|</row>
    <row>|....................\.............................|</row>
    <row>|.....................\............................|</row>
    <row>|......................\...........................|</row>
    <row>|.......................\..........................|</row>
    <row>|........................User......................|</row>
    <row>+---------------------------------------------------</row>
  </neuromap>
</mindmap>
